core_evals/hle/__init__.py
core_evals/hle/framework.yml
core_evals/hle/framework_entrypoint.py
core_evals/hle/output.py
hle_eval/__init__.py
hle_eval/common.py
hle_eval/entrypoint.py
hle_eval/nv_utils.py
hle_eval/run_judge_results.py
hle_eval/run_model_predictions.py
hle_eval/utils.py
nvidia_hle-25.11.dist-info/licenses/LICENSE
nvidia_hle-25.11.dist-info/METADATA
nvidia_hle-25.11.dist-info/WHEEL
nvidia_hle-25.11.dist-info/entry_points.txt
nvidia_hle-25.11.dist-info/top_level.txt
nvidia_hle-25.11.dist-info/RECORD
